pdf_struct/__init__.py
pdf_struct/_version.py
pdf_struct/cli.py
pdf_struct/core/__init__.py
pdf_struct/core/clustering.py
pdf_struct/core/data_statistics.py
pdf_struct/core/document.py
pdf_struct/core/download.py
pdf_struct/core/evaluation.py
pdf_struct/core/export.py
pdf_struct/core/feature_extractor.py
pdf_struct/core/predictor.py
pdf_struct/core/preprocessing.py
pdf_struct/core/structure_evaluation.py
pdf_struct/core/transition_labels.py
pdf_struct/core/utils.py
pdf_struct/export/__init__.py
pdf_struct/export/hocr.py
pdf_struct/feature_extractor/__init__.py
pdf_struct/feature_extractor/hocr_balance_sheet_ja.py
pdf_struct/feature_extractor/pdf_contract.py
pdf_struct/feature_extractor/pdf_contract_ja.py
pdf_struct/feature_extractor/text_contract.py
pdf_struct/features/__init__.py
pdf_struct/features/lexical.py
pdf_struct/features/lm.py
pdf_struct/features/listing/__init__.py
pdf_struct/features/listing/base.py
pdf_struct/features/listing/en.py
pdf_struct/features/listing/ja.py
pdf_struct/loader/__init__.py
pdf_struct/loader/hocr.py
pdf_struct/loader/pdf.py
pdf_struct/loader/text.py
pdf_struct-0.3.4.dist-info/LICENSE
pdf_struct-0.3.4.dist-info/METADATA
pdf_struct-0.3.4.dist-info/WHEEL
pdf_struct-0.3.4.dist-info/entry_points.txt
pdf_struct-0.3.4.dist-info/top_level.txt
pdf_struct-0.3.4.dist-info/RECORD
