Metadata-Version: 2.1
Name: pdf-struct
Version: 0.3.4
Summary: Logical structure analysis of visually structured documents.
Home-page: https://github.com/stanfordnlp/pdf-struct
Author: Yuta Koreeda
Author-email: yuta.koreeda@hal.hitachi.com
Maintainer: Yuta Koreeda
Maintainer-email: yuta.koreeda@hal.hitachi.com
License: Apache
Platform: UNKNOWN
Classifier: Environment :: Console
Classifier: Development Status :: 4 - Beta
Classifier: Intended Audience :: Developers
Classifier: Intended Audience :: Education
Classifier: Intended Audience :: Science/Research
Classifier: License :: OSI Approved :: Apache Software License
Classifier: Operating System :: OS Independent
Classifier: Programming Language :: Python :: 3.8
Classifier: Topic :: Scientific/Engineering :: Artificial Intelligence
Classifier: Topic :: Scientific/Engineering :: Information Analysis
Requires-Dist: click (==8.1.3)
Requires-Dist: numpy (==1.23.1)
Requires-Dist: pdfminer.six (==20220524)
Requires-Dist: regex (==2022.7.25)
Requires-Dist: torch (==1.9.0)
Requires-Dist: tqdm (==4.48.0)
Requires-Dist: transformers (==4.9.1)
Requires-Dist: scikit-learn (==1.1.2)
Requires-Dist: joblib (==1.0.0)
Requires-Dist: editdistance (==0.5.3)
Requires-Dist: beautifulsoup4 (==4.11.1)
Requires-Dist: sentencepiece (==0.1.96)
Requires-Dist: wheel
Requires-Dist: twine
